MANIFEST.in
README.md
requirements.txt
setup.py
dingapi/__init__.py
dingapi/cache.py
dingapi/client.py
dingapi/exception.py
dingapi.egg-info/PKG-INFO
dingapi.egg-info/SOURCES.txt
dingapi.egg-info/dependency_links.txt
dingapi.egg-info/requires.txt
dingapi.egg-info/top_level.txt
dingapi/apis/__init__.py
dingapi/apis/base.py
dingapi/apis/department.py
dingapi/apis/media.py
dingapi/apis/message.py
dingapi/apis/user.py