Metadata-Version: 2.1
Name: dingapi
Version: 0.0.6
Summary: lightweight dingtalk api for python
Home-page: https://github.com/hongjinpin/dingapi
Author: hongjinpin
Author-email: hongjinpin@qq.com
License: UNKNOWN
Keywords: dingding,ding,dtalk,dingtalk,sdk,api
Platform: UNKNOWN
Classifier: Programming Language :: Python :: 3
Classifier: License :: OSI Approved :: MIT License
Classifier: Operating System :: OS Independent
Requires-Python: >=3.6
